
{"data"  : [{
        "amount": 120,
        "date": "10-12-2022"
      },{
        "amount": 55,
        "date": "10-13-2022"
      },
      {
        "amount": 180,
        "date": "10-14-2022"
      },
        {
        "amount": 90,
        "date": "10-15-2022"
      },
        {
        "amount": 20,
        "date": "09-16-2019"
      },
        {
        "amount": -20,
        "date": "09-17-2019"
      },
        {
        "amount": -55,
        "date": "09-18-2019"
      },
      {
        "amount": 75,
        "date": "09-18-2019"
      },
        {
        "amount": 155,
        "date": "08-19-2019"
      },
        {
        "amount": 100,
        "date": "08-20-2019"
      } 
      ]
    }
  